deltaextras/__init__.py
deltaextras/rorder_setup.py
deltaextras/utils/__init__.py
deltaextras/utils/_utils.py
deltaextras/utils/sortunique.py
deltaextra-0.0.3.dist-info/LICENSE
deltaextra-0.0.3.dist-info/METADATA
deltaextra-0.0.3.dist-info/WHEEL
deltaextra-0.0.3.dist-info/top_level.txt
deltaextra-0.0.3.dist-info/RECORD
