Metadata-Version: 2.1
Name: deltaextra
Version: 0.0.3
Summary: A couple extra features to tack on to delta
Author-email: Dean MacGregor <powertrading121@gmail.com>
Requires-Python: >=3.8
License-File: LICENSE
Requires-Dist: deltalake
Requires-Dist: pyarrow
Requires-Dist: pyarrow-stubs
